sortedcontainers/__init__.py
sortedcontainers/sorteddict.py
sortedcontainers/sortedlist.py
sortedcontainers/sortedset.py
sortedcontainers-2.2.2.dist-info/LICENSE
sortedcontainers-2.2.2.dist-info/METADATA
sortedcontainers-2.2.2.dist-info/WHEEL
sortedcontainers-2.2.2.dist-info/top_level.txt
sortedcontainers-2.2.2.dist-info/RECORD
